fapesp_opportunities/__init__.py
fapesp_opportunities/about.py
fapesp_opportunities/desktop.py
fapesp_opportunities/program.py
fapesp_opportunities/icons/logo.png
fapesp_opportunities/modules/__init__.py
fapesp_opportunities/modules/configure.py
fapesp_opportunities/modules/fapesp.py
fapesp_opportunities/modules/wabout.py
fapesp_opportunities-0.1.9.dist-info/licenses/LICENSE
fapesp_opportunities-0.1.9.dist-info/METADATA
fapesp_opportunities-0.1.9.dist-info/WHEEL
fapesp_opportunities-0.1.9.dist-info/entry_points.txt
fapesp_opportunities-0.1.9.dist-info/top_level.txt
fapesp_opportunities-0.1.9.dist-info/RECORD
