Metadata-Version: 2.4
Name: fapesp_opportunities
Version: 0.1.9
Summary: Program to list FAPESP opportunities
Author-email: Fernando Pujaico Rivera <fernando.pujaico.rivera@gmail.com>
Maintainer-email: Fernando Pujaico Rivera <fernando.pujaico.rivera@gmail.com>
License-Expression: GPL-3.0-only WITH Classpath-exception-2.0 OR BSD-3-Clause
Project-URL: Bug Reports, https://github.com/trucomanx/FapespOpportunities/issues
Project-URL: Funding, https://trucomanx.github.io/en/funding.html
Project-URL: Source, https://github.com/trucomanx/FapespOpportunities
Keywords: FAPESP,research,funding,scholarships,grants,Brazil
Classifier: Programming Language :: Python :: 3
Classifier: Operating System :: OS Independent
Requires-Python: >=3.8
License-File: LICENSE
Requires-Dist: PyQt5
Requires-Dist: requests
Requires-Dist: beautifulsoup4
Dynamic: license-file
